manim_circuit/__init__.py
manim_circuit/mobjects.py
manim_circuit/utils.py
manim_circuit-0.0.3.dist-info/METADATA
manim_circuit-0.0.3.dist-info/WHEEL
manim_circuit-0.0.3.dist-info/entry_points.txt
manim_circuit-0.0.3.dist-info/RECORD
