Metadata-Version: 2.3
Name: manim-circuit
Version: 0.0.3
Summary: A manim-plugin that adds custom circuit VMobject(s)
Home-page: https://github.com/Mr-FuzzyPenguin/manim-circuit
License: MIT
Keywords: manim,plugins,circuit
Author: Mr-FuzzyPenguin
Author-email: rubikscubeworld2014@gmail.com
Requires-Python: >=3.9,<3.13
Classifier: License :: OSI Approved :: MIT License
Classifier: Programming Language :: Python :: 3
Classifier: Programming Language :: Python :: 3.9
Classifier: Programming Language :: Python :: 3.10
Classifier: Programming Language :: Python :: 3.11
Classifier: Programming Language :: Python :: 3.12
Requires-Dist: manim (>=0.18)
Project-URL: Repository, https://github.com/Mr-FuzzyPenguin/manim-circuit
